src/__init__.py
src/collection.py
src/end_point.py
src/main.py
src/parser.py
src/sync_ends_service.py
test/__init__.py
test/test_collection.py
test/test_end_point.py
test/test_main.py
test/test_parser.py
test/test_sync_ends_service.py
sync_ends-2.1.3.dist-info/LICENSE
sync_ends-2.1.3.dist-info/METADATA
sync_ends-2.1.3.dist-info/WHEEL
sync_ends-2.1.3.dist-info/entry_points.txt
sync_ends-2.1.3.dist-info/top_level.txt
sync_ends-2.1.3.dist-info/RECORD
