Metadata-Version: 2.1
Name: sync-ends
Version: 2.1.3
Summary: Sync Ends - End Development Overheads CSC 510 Project
Home-page: https://github.com/jaymodi98/csc510-project
Author: Chintan Gandhi, Jay Modi, Suraj Patel, Omkar Kulkarni, Nirav Shah
Author-email: cagandhi97@gmail.com
License: UNKNOWN
Download-URL: https://github.com/jaymodi98/Sync-Ends/archive/v2.1.3.tar.gz
Keywords: python
Platform: UNKNOWN
Classifier: Programming Language :: Python :: 3
Classifier: License :: OSI Approved :: MIT License
Classifier: Operating System :: OS Independent
Requires-Python: >=3.6
Requires-Dist: aiohttp (==3.6.3)
Requires-Dist: appdirs (==1.4.4)
Requires-Dist: async-timeout (==3.0.1)
Requires-Dist: attrs (==20.2.0)
Requires-Dist: black (==20.8b1)
Requires-Dist: certifi (==2020.6.20)
Requires-Dist: chardet (==3.0.4)
Requires-Dist: click (==7.1.2)
Requires-Dist: coverage
Requires-Dist: flake8 (==3.8.4)
Requires-Dist: idna (==2.10)
Requires-Dist: importlib-metadata (==2.0.0)
Requires-Dist: iniconfig (==1.1.1)
Requires-Dist: jsondiff (==1.2.0)
Requires-Dist: mccabe (==0.6.1)
Requires-Dist: multidict (==4.7.6)
Requires-Dist: mypy-extensions (==0.4.3)
Requires-Dist: packaging (==20.4)
Requires-Dist: pathspec (==0.8.0)
Requires-Dist: pluggy (==0.13.1)
Requires-Dist: py (==1.9.0)
Requires-Dist: pycodestyle (==2.6.0)
Requires-Dist: pyflakes (==2.2.0)
Requires-Dist: pyparsing (==2.4.7)
Requires-Dist: pytest (==6.1.1)
Requires-Dist: pytest-cov (==2.10.1)
Requires-Dist: pytest-flake8 (==1.0.6)
Requires-Dist: regex (==2020.10.23)
Requires-Dist: requests (==2.24.0)
Requires-Dist: six (==1.15.0)
Requires-Dist: slack (==0.0.2)
Requires-Dist: slackclient (==2.9.2)
Requires-Dist: toml (==0.10.1)
Requires-Dist: typed-ast (==1.4.1)
Requires-Dist: typing-extensions (==3.7.4.3)
Requires-Dist: urllib3 (==1.25.10)
Requires-Dist: websocket-client (==0.54.0)
Requires-Dist: yarl (==1.5.1)
Requires-Dist: zipp (==3.4.0)
